rdk/__init__.py
rdk/cli.py
rdk/rdk.py
rdk/rdklib_versions.yaml
rdk/supported_resource_types.yaml
rdk/template/configManagedRule.yaml
rdk/template/configManagedRuleOrganization.yaml
rdk/template/configManagedRuleWithRemediation.yaml
rdk/template/configRule.yaml
rdk/template/configRuleAssumeRolePolicyDoc.json
rdk/template/configRuleOrganization.yaml
rdk/template/deliveryPermissionsPolicy.json
rdk/template/example_ci/AWS_ACM_Certificate.json
rdk/template/example_ci/AWS_ApiGatewayV2_Api.json
rdk/template/example_ci/AWS_ApiGatewayV2_Stage.json
rdk/template/example_ci/AWS_ApiGateway_RestApi.json
rdk/template/example_ci/AWS_ApiGateway_Stage.json
rdk/template/example_ci/AWS_AutoScaling_AutoScalingGroup.json
rdk/template/example_ci/AWS_AutoScaling_LaunchConfiguration.json
rdk/template/example_ci/AWS_AutoScaling_ScalingPolicy.json
rdk/template/example_ci/AWS_AutoScaling_ScheduledAction.json
rdk/template/example_ci/AWS_CLOUDFRONT_DISTRIBUTION.json
rdk/template/example_ci/AWS_CLOUDFRONT_STREAMINGDISTRIBUTION.json
rdk/template/example_ci/AWS_CloudFormation_Stack.json
rdk/template/example_ci/AWS_CloudWatch_Alarm.json
rdk/template/example_ci/AWS_Cloudtrail_Trail.json
rdk/template/example_ci/AWS_CodeBuild_Project.json
rdk/template/example_ci/AWS_CodePipeline_Pipeline.json
rdk/template/example_ci/AWS_DynamoDB_Table.json
rdk/template/example_ci/AWS_EC2_CapacityReservation.json
rdk/template/example_ci/AWS_EC2_CustomerGateway.json
rdk/template/example_ci/AWS_EC2_EIP.json
rdk/template/example_ci/AWS_EC2_FlowLog.json
rdk/template/example_ci/AWS_EC2_Host.json
rdk/template/example_ci/AWS_EC2_Instance.json
rdk/template/example_ci/AWS_EC2_InternetGateway.json
rdk/template/example_ci/AWS_EC2_LaunchTemplate.json
rdk/template/example_ci/AWS_EC2_NatGateway.json
rdk/template/example_ci/AWS_EC2_NetworkAcl.json
rdk/template/example_ci/AWS_EC2_NetworkInterface.json
rdk/template/example_ci/AWS_EC2_RouteTable.json
rdk/template/example_ci/AWS_EC2_SecurityGroup.json
rdk-0.17.22.dist-info/METADATA
rdk-0.17.22.dist-info/WHEEL
rdk-0.17.22.dist-info/entry_points.txt
rdk-0.17.22.dist-info/licenses/LICENSE
rdk-0.17.22.dist-info/licenses/NOTICE.txt
rdk-0.17.22.dist-info/RECORD
