Metadata-Version: 2.4
Name: rdk
Version: 0.17.22
Summary: Rule Development Kit CLI for AWS Config
License: Apache-2.0
License-File: LICENSE
License-File: NOTICE.txt
Keywords: amazon,aws,awslabs,rdk,config,rules,compliance
Author: AWS RDK Maintainers
Author-email: rdk-maintainers@amazon.com
Requires-Python: >=3.10.0,<4.0.0
Classifier: License :: OSI Approved :: Apache Software License
Classifier: Programming Language :: Python
Classifier: Programming Language :: Python :: 3
Classifier: Programming Language :: Python :: 3.10
Classifier: Programming Language :: Python :: 3.11
Classifier: Programming Language :: Python :: 3.12
Classifier: Programming Language :: Python :: 3.13
Classifier: Programming Language :: Python :: 3.14
Classifier: Programming Language :: Python :: 3.7
Classifier: Programming Language :: Python :: 3.8
Classifier: Programming Language :: Python :: 3.9
Requires-Dist: boto3 (>=1.35.0,<2.0.0)
Requires-Dist: configargparse (>=1.7.1,<2.0.0)
Requires-Dist: cryptography (>=44.0.2,<45.0.0)
Requires-Dist: pycares (>=4.9.0,<5.0.0)
Requires-Dist: pyyaml (>=6.0,<7.0)
Requires-Dist: requests (>=2.32.4,<3.0.0)
Project-URL: Documentation, https://aws-config-rdk.readthedocs.io
Project-URL: Homepage, https://github.com/awslabs/aws-config-rdk
Project-URL: Repository, https://github.com/awslabs/aws-config-rdk
